davidkhala/amap/__init__.py
davidkhala_amap-0.0.1.dist-info/METADATA
davidkhala_amap-0.0.1.dist-info/WHEEL
davidkhala_amap-0.0.1.dist-info/RECORD
