Metadata-Version: 2.4
Name: davidkhala.amap
Version: 0.0.1
Summary: Add your description here
Requires-Python: >=3.10
Requires-Dist: davidkhala-utils[http-request]
